netbox_interface_view/__init__.py
netbox_interface_view/template_content.py
netbox_interface_view/tests.py
netbox_interface_view/urls.py
netbox_interface_view/views.py
netbox_interface_view/template_content/device.html
netbox_interface_view/templates/netbox_interface_view/interface_grid.html
netbox_interface_view/templates/netbox_interface_view/rack_interface_grid.html
netbox_interface_view/templates/netbox_interface_view/rack_interface_grid_mock.html
netbox_interface_view-0.2.12.dist-info/METADATA
netbox_interface_view-0.2.12.dist-info/WHEEL
netbox_interface_view-0.2.12.dist-info/top_level.txt
netbox_interface_view-0.2.12.dist-info/RECORD
