Metadata-Version: 2.4
Name: netbox-interface-view
Version: 0.2.12
Summary: NetBox Plugin for viewing interfaces in a grid layout with VLAN color-coding
Home-page: https://github.com/ITW-Welding-AB/netbox-plugin-interface-view
Author: Tolfx
License: Apache 2.0
Keywords: netbox plugin interface grid visualization
Classifier: Development Status :: 4 - Beta
Classifier: Framework :: Django
Classifier: Intended Audience :: System Administrators
Classifier: License :: OSI Approved :: Apache Software License
Classifier: Programming Language :: Python :: 3
Classifier: Programming Language :: Python :: 3.8
Classifier: Programming Language :: Python :: 3.9
Classifier: Programming Language :: Python :: 3.10
Classifier: Programming Language :: Python :: 3.11
Classifier: Programming Language :: Python :: 3.12
Requires-Python: >=3.8
Dynamic: author
Dynamic: classifier
Dynamic: description
Dynamic: description-content-type
Dynamic: home-page
Dynamic: keywords
Dynamic: license
Dynamic: requires-python
Dynamic: summary
